cch/__init__.py
cch/cli.py
cch-0.1.19.dist-info/DESCRIPTION.rst
cch-0.1.19.dist-info/entry_points.txt
cch-0.1.19.dist-info/METADATA
cch-0.1.19.dist-info/metadata.json
cch-0.1.19.dist-info/RECORD
cch-0.1.19.dist-info/top_level.txt
cch-0.1.19.dist-info/WHEEL
